vulnerabilities/__init__.py
vulnerabilities/admin.py
vulnerabilities/api.py
vulnerabilities/api_extension.py
vulnerabilities/api_v2.py
vulnerabilities/forms.py
vulnerabilities/import_runner.py
vulnerabilities/importer.py
vulnerabilities/improve_runner.py
vulnerabilities/improver.py
vulnerabilities/lib_oval.py
vulnerabilities/lib_oval.py.ABOUT
vulnerabilities/lib_oval.py.LICENSE
vulnerabilities/models.py
vulnerabilities/oval_parser.py
vulnerabilities/pagination.py
vulnerabilities/references.py
vulnerabilities/risk.py
vulnerabilities/rpm_utils.py
vulnerabilities/schedules.py
vulnerabilities/severity_systems.py
vulnerabilities/tasks.py
vulnerabilities/throttling.py
vulnerabilities/utils.py
vulnerabilities/views.py
vulnerabilities/weight_config.py
vulnerabilities/importers/__init__.py
vulnerabilities/importers/apache_httpd.py
vulnerabilities/importers/apache_kafka.py
vulnerabilities/importers/apache_tomcat.py
vulnerabilities/importers/archlinux.py
vulnerabilities/importers/curl.py
vulnerabilities/importers/debian.py
vulnerabilities/importers/debian_oval.py
vulnerabilities/importers/elixir_security.py
vulnerabilities/importers/epss.py
vulnerabilities/importers/fireeye.py
vulnerabilities/importers/gentoo.py
vulnerabilities/importers/github_osv.py
vulnerabilities/importers/gsd.py
vulnerabilities/importers/istio.py
vulnerabilities/importers/kaybee.py
vulnerabilities/importers/mattermost.py
vulnerabilities/importers/mozilla.py
vulnerabilities/importers/openssl.py
vulnerabilities/importers/oss_fuzz.py
vulnerabilities/importers/osv.py
vulnerabilities/importers/postgresql.py
vulnerabilities/importers/project_kb_msr2019.py
vulnerabilities/importers/redhat.py
vulnerabilities/importers/retiredotnet.py
vulnerabilities/importers/ruby.py
vulnerabilities/importers/rust.py
vulnerabilities/importers/suse_backports.py
vulnerabilities/importers/suse_oval.py
vulnerabilities/importers/suse_scores.py
vulnerabilities/importers/ubuntu.py
vulnerabilities/importers/ubuntu_usn.py
vulnerablecode-36.1.3.dist-info/licenses/AUTHORS.rst
vulnerablecode-36.1.3.dist-info/licenses/CHANGELOG.rst
vulnerablecode-36.1.3.dist-info/licenses/NOTICE
vulnerablecode-36.1.3.dist-info/licenses/README.rst
vulnerablecode-36.1.3.dist-info/licenses/apache-2.0.LICENSE
vulnerablecode-36.1.3.dist-info/licenses/cc-by-sa-4.0.LICENSE
vulnerablecode-36.1.3.dist-info/METADATA
vulnerablecode-36.1.3.dist-info/WHEEL
vulnerablecode-36.1.3.dist-info/entry_points.txt
vulnerablecode-36.1.3.dist-info/top_level.txt
vulnerablecode-36.1.3.dist-info/RECORD
