Metadata-Version: 2.4
Name: vulnerablecode
Version: 36.1.3
Summary: VulnerableCode is a free and open database of open source software package vulnerabilities because open source software vulnerabilities data and tools should be free and open source themselves.
Home-page: https://github.com/nexB/vulnerablecode
Author: nexB. Inc. and others
Author-email: info@aboutcode.org
License: Apache-2.0 AND CC-BY-SA-4.0
Keywords: open source,vulnerability,security,cve,purl,packageurl,dependency,package,vulnerability-db,SBOM,sca
Classifier: Development Status :: 4 - Beta
Classifier: Intended Audience :: Developers
Classifier: Programming Language :: Python :: 3
Classifier: Programming Language :: Python :: 3 :: Only
Classifier: Programming Language :: Python :: 3.8
Classifier: Programming Language :: Python :: 3.9
Classifier: Programming Language :: Python :: 3.10
Classifier: Topic :: Software Development
Classifier: Topic :: Utilities
Classifier: Topic :: Security
Classifier: Topic :: Software Development :: Bug Tracking
Classifier: Framework :: Django
Requires-Python: >=3.9
License-File: apache-2.0.LICENSE
License-File: cc-by-sa-4.0.LICENSE
License-File: NOTICE
License-File: AUTHORS.rst
License-File: CHANGELOG.rst
License-File: README.rst
Requires-Dist: Django<=5.0,>=4.2.0
Requires-Dist: psycopg2-binary>=2.8.6
Requires-Dist: djangorestframework>=3.15.0
Requires-Dist: django-extensions>=3.2.3
Requires-Dist: django-filter>=24.0
Requires-Dist: django-widget-tweaks>=1.5.0
Requires-Dist: django-crispy-forms>=2.3
Requires-Dist: crispy-bootstrap4>=2024.1
Requires-Dist: django-environ>=0.11.0
Requires-Dist: gunicorn>=23.0.0
Requires-Dist: drf-spectacular[sidecar]>=0.24.2
Requires-Dist: packageurl-python>=0.15
Requires-Dist: univers>=30.12.0
Requires-Dist: license-expression>=30.0.0
Requires-Dist: binaryornot>=0.4.4
Requires-Dist: saneyaml>=0.6.0
Requires-Dist: beautifulsoup4>=4.9.3
Requires-Dist: python-dateutil>=2.8.1
Requires-Dist: toml>=0.10.2
Requires-Dist: lxml>=4.6.4
Requires-Dist: defusedxml>=0.7.1
Requires-Dist: Markdown>=3.3.0
Requires-Dist: dateparser>=1.1.1
Requires-Dist: cvss>=2.4
Requires-Dist: cwe2>=3.0.0
Requires-Dist: GitPython>=3.1.17
Requires-Dist: requests>=2.25.1
Requires-Dist: fetchcode>=0.6.0
Requires-Dist: aboutcode.pipeline>=0.1.0
Requires-Dist: django-rq==2.10.1
Requires-Dist: rq-scheduler==0.13.1
Requires-Dist: python-dotenv
Requires-Dist: texttable
Requires-Dist: django-recaptcha>=4.0.0
Provides-Extra: dev
Requires-Dist: pycodestyle>=2.8.0; extra == "dev"
Requires-Dist: black>=22.3.0; extra == "dev"
Requires-Dist: isort>=5.10.1; extra == "dev"
Requires-Dist: doc8>=0.11.1; extra == "dev"
Requires-Dist: Sphinx>=4.5.0; extra == "dev"
Requires-Dist: sphinx_rtd_theme>=1.0.0; extra == "dev"
Requires-Dist: sphinxcontrib-django2>=1.5; extra == "dev"
Requires-Dist: sphinx-autobuild>=2024.10.3; extra == "dev"
Requires-Dist: pytest>=7.0.1; extra == "dev"
Requires-Dist: pytest-django>=4.5.2; extra == "dev"
Requires-Dist: freezegun>=1.1.0; extra == "dev"
Requires-Dist: ipython==8.10.0; extra == "dev"
Requires-Dist: commoncode; extra == "dev"
Requires-Dist: django-debug-toolbar; extra == "dev"
Requires-Dist: pyinstrument; extra == "dev"
Requires-Dist: flot; extra == "dev"
Requires-Dist: twine; extra == "dev"
Dynamic: license-file
